[{"ai_meta":{},"author":["inokii"],"created_at":"2025-09-11T11:45:34Z","description":"A simple workflow that runs all Phoenix Contact related nuclei templates on a given target.","dir":"workflows","filename":"phoenix-contact-workflow.yaml","id":"phoenix-contact-workflow","is_draft":false,"is_early":true,"is_github":false,"is_new":false,"is_pdresearch":false,"is_pdteam":false,"is_pdtemplate":false,"name":"Phoenix Contact Security Checks","raw":"id: phoenix-contact-workflow\n\ninfo:\n  name: Phoenix Contact Security Checks\n  author: inokii\n  description: A simple workflow that runs all Phoenix Contact related nuclei templates on a given target.\n\nworkflows:\n  - template: http/exposed-panels/phoenix-contact-charx-panel.yaml\n    subtemplates:\n      - tags: phoenix-contact\n","ref":"projectdiscovery/nuclei-templates:ca380a3636cb","severity":"unknown","template_id":"phoenix-contact-workflow","template_type":"public","type":"workflow","updated_at":"2025-09-11T11:45:34Z","uri":"workflows/phoenix-contact-workflow.yaml"},{"ai_meta":{},"author":["inokii"],"created_at":"2025-09-11T11:45:34Z","description":"Phoenix Contact CHARX SEC-3XXX AC Charging Controller panel was detected.\n","digest":"4b0a004830460221009c3d4f49e72b7f97dd67f9ecaccf8b706b52faff3c91a91036b948c0a660ff1d02210087b687af1b23109ee1165f10570751d107d56d5197f5d7b3c73b5b2c71679c9f:922c64590222798bb761d5b6d8e72950","dir":"http/exposed-panels","filename":"phoenix-contact-charx-panel.yaml","id":"phoenix-contact-charx-panel","is_draft":false,"is_early":true,"is_github":false,"is_new":false,"is_pdresearch":false,"is_pdteam":false,"is_pdtemplate":false,"metadata":{"max-request":1,"shodan-query":"title:\"Phoenix Contact - CHARX\"","verified":true},"name":"Phoenix Contact CHARX SEC-3XXX AC Charging Controller Panel - Detect","raw":"id: phoenix-contact-charx-panel\n\ninfo:\n  name: Phoenix Contact CHARX SEC-3XXX AC Charging Controller Panel - Detect\n  author: inokii\n  severity: info\n  description: |\n    Phoenix Contact CHARX SEC-3XXX AC Charging Controller panel was detected.\n  reference:\n    - https://www.phoenixcontact.com/en-us/products/ac-charging-controllers\n  metadata:\n    verified: true\n    max-request: 1\n    shodan-query: title:\"Phoenix Contact - CHARX\"\n  tags: panel,phoenix-contact,charx,ics\n\nhttp:\n  - method: GET\n    path:\n      - \"{{BaseURL}}\"\n\n    matchers-condition: and\n    matchers:\n      - type: word\n        part: body\n        words:\n          - \"\u003ctitle\u003ePhoenix Contact - CHARX\u003c/title\u003e\"\n\n      - type: status\n        status:\n          - 200\n# digest: 4b0a004830460221009c3d4f49e72b7f97dd67f9ecaccf8b706b52faff3c91a91036b948c0a660ff1d02210087b687af1b23109ee1165f10570751d107d56d5197f5d7b3c73b5b2c71679c9f:922c64590222798bb761d5b6d8e72950","ref":"projectdiscovery/nuclei-templates:ca380a3636cb","references":["https://www.phoenixcontact.com/en-us/products/ac-charging-controllers"],"severity":"info","tags":["panel","phoenix-contact","charx","ics"],"template_id":"phoenix-contact-charx-panel","template_type":"public","type":"http","updated_at":"2025-09-11T11:47:59.969958609Z","uri":"http/exposed-panels/phoenix-contact-charx-panel.yaml"}]
